{
  "SMS": {
    "API_KEY": "",
    "TEMPLATE_ID": "",
    "LINE_NUMBER": ""
  },
  "UPLOAD": {
    "TEMP_PATH": "tmp/uploads",
    "DOWNLOAD_HOST": "https://dl.zareoon.ir",
    "MAX_FILE_SIZE": 5242880,
    "ALLOWED_MIMES": [
      "image/jpeg",
      "image/png",
      "image/gif",
      "application/pdf",
      "application/msword",
      "application/vnd.openxmlformats-officedocument.wordprocessingml.document"
    ],
    "FTP": {
      "host": "dl.zareoon.ir",
      "port": 21,
      "user": "pz22008",
      "password": "L3SvlSZC",
      "secure": false,
      "basePath": "/public_html"
    },
    "PATHS": {
      "users": {
        "avatars": "media/users/avatars",
        "documents": "media/users/documents",
        "temp": "media/users/temp"
      },
      "products": {
        "images": "media/products/images",
        "videos": "media/products/videos",
        "documents": "media/products/documents",
        "icons": "media/products/icons"
      },
      "inventory": {
        "images": "media/inventory/images",
        "documents": "media/inventory/documents",
        "certificates": "media/inventory/certificates"
      },
      "orders": {
        "invoices": "media/orders/invoices",
        "receipts": "media/orders/receipts",
        "contracts": "media/orders/contracts",
        "shipping": "media/orders/shipping"
      },
      "locations": {
        "images": "media/locations/images",
        "maps": "media/locations/maps",
        "documents": "media/locations/documents"
      },
      "attributes": {
        "documents": "media/attributes/documents"
      },
      "system": {
        "temp": "media/system/temp",
        "backups": "media/system/backups",
        "logs": "media/system/logs"
      },
      "shared": {
        "templates": "media/shared/templates",
        "icons": "media/shared/icons",
        "banners": "media/shared/banners",
        "default": "media/shared/default"
      }
    }
  },
  "PORT": 3000,
  "DB_HOST": "localhost",
  "DB_USER": "root",
  "DB_PASS": "",
  "DB_NAME": "farmer",
  "JWT_SECRET": "your-secret-key",
  "FRONTEND_URL": "http://localhost:3000"
}
